pr/__init__.py
pr/pr.py
pr/tabulate.py
pr-0.6.0.dist-info/LICENSE
pr-0.6.0.dist-info/METADATA
pr-0.6.0.dist-info/WHEEL
pr-0.6.0.dist-info/top_level.txt
pr-0.6.0.dist-info/RECORD
